app/hello.py
drmlapp-1.0.6.dist-info/DESCRIPTION.rst
drmlapp-1.0.6.dist-info/METADATA
drmlapp-1.0.6.dist-info/RECORD
drmlapp-1.0.6.dist-info/WHEEL
drmlapp-1.0.6.dist-info/metadata.json
drmlapp-1.0.6.dist-info/top_level.txt
