Metadata-Version: 2.0
Name: drmlapp
Version: 1.0.6
Summary: UNKNOWN
Home-page: UNKNOWN
Author: Sumanth Simha, Nagaraj G
Author-email: ssimha152@gmail.com
License: UNKNOWN
Platform: UNKNOWN
Requires-Python: >=3.6.0
Requires-Dist: flask (==1.0.2)
Requires-Dist: keras (==2.2.4)
Requires-Dist: numpy (==1.16.2)
Requires-Dist: pillow (==6.0.0)
Requires-Dist: scipy (==1.0.0)
Requires-Dist: tensorflow (==1.13.1)
Requires-Dist: werkzeug (==0.15.1)
